{
"layout": {
  "startPoint": {
    "X": 0,
    "Y": 200
  },
  "oscPath": "layout1",
  "decorator": "Flowlayout",
  "backgroundColor": "blueColor",
  "replaceCurrent": false,
  "uiObjects": [
    {
      "prototypeName": "sendButton",
      "size": {
        "Width": 100,
        "Height": 44
      },
      "oscPath": "/goodbye"
    },
    {
      "prototypeName": "sendButton",
      "size": {
        "Width": 40,
        "Height": 44
      },
      "oscPath": "/goodbye2"
    },

    {
      "prototypeName": "sendSlider",
      "size": {
        "Width": 100,
        "Height": 44
      },
      "oscPath": "/slider"
    },
    {
      "prototypeName": "textLabel",
      "size": {
        "Width": 100,
        "Height": 44
      },
      "oscPath": "/label"
    }
  ]
}
}
